adafruit_circuitpython_waveform-1.3.25.dist-info/licenses/LICENSE
adafruit_waveform/__init__.py
adafruit_waveform/sine.py
adafruit_waveform/square.py
adafruit_circuitpython_waveform-1.3.25.dist-info/METADATA
adafruit_circuitpython_waveform-1.3.25.dist-info/WHEEL
adafruit_circuitpython_waveform-1.3.25.dist-info/top_level.txt
adafruit_circuitpython_waveform-1.3.25.dist-info/RECORD
