Metadata-Version: 2.4
Name: adafruit-circuitpython-waveform
Version: 1.3.25
Summary: CircuitPython library for generating simple waveforms for audio.
Author-email: Adafruit Industries <circuitpython@adafruit.com>
License: MIT
Project-URL: Homepage, https://github.com/adafruit/Adafruit_CircuitPython_Waveform
Keywords: adafruit,haptic,waveform,signal,audio,rtttl,sine,squarewave,hardware,micropython,circuitpython
Classifier: Intended Audience :: Developers
Classifier: Topic :: Software Development :: Libraries
Classifier: Topic :: Software Development :: Embedded Systems
Classifier: Topic :: System :: Hardware
Classifier: License :: OSI Approved :: MIT License
Classifier: Programming Language :: Python :: 3
License-File: LICENSE
Provides-Extra: optional
Dynamic: license-file
